omnicloud/tools/__init__.py
omnicloud/tools/duty/__init__.py
omnicloud/tools/duty/common.py
omnicloud/tools/duty/gcp.py
omnicloud/tools/duty/mkdocs.py
omnicloud_tools-0.0.1.dist-info/LICENSE
omnicloud_tools-0.0.1.dist-info/METADATA
omnicloud_tools-0.0.1.dist-info/WHEEL
omnicloud_tools-0.0.1.dist-info/RECORD
