Metadata-Version: 2.1
Name: omnicloud-tools
Version: 0.0.1
Summary: collection of duties
Home-page: https://omnicloud.world/
Keywords: duty,routine
Author: Iurii Tarasenko
Author-email: iurii@omnicloud.world
Requires-Python: >=3.10,<4.0
Classifier: Intended Audience :: Developers
Classifier: Intended Audience :: Information Technology
Classifier: License :: OSI Approved :: MIT License
Classifier: Programming Language :: Python :: 3
Classifier: Programming Language :: Python :: 3.10
Classifier: Programming Language :: Python :: 3.11
Classifier: Programming Language :: Python :: 3.10
Classifier: Topic :: Software Development :: Libraries :: Python Modules
Requires-Dist: cryptography (>=40.0.1,<41.0.0)
Requires-Dist: duty (>=0.9.0,<0.10.0)
Requires-Dist: google-auth (>=2.17.0,<3.0.0)
Requires-Dist: requests (>=2.28.2,<3.0.0)
Project-URL: Documentation, https://docs.omnicloud.world/py-tools
Project-URL: Repository, https://github.com/omnicloudworld/py.tools
